[
{"source": "https://playbook.draftkings.com/nba/nba-targets-January-27th-4", "targets": []},
{"source": "https://playbook.draftkings.com/nba/nba-targets-January-27th-1", "targets": []},
{"source": "https://playbook.draftkings.com/nba/nba-cheat-sheet-January-27th-2", "targets": [{"value": 2, "name": "Isaiah Thomas"}, {"value": -2, "name": "Jrue Holiday"}, {"value": 2, "name": "Bradley Beal"}, {"value": 2, "name": "LeBron James"}, {"value": -2, "name": "Tyreke Evans"}, {"value": 2, "name": "DeMarcus Cousins"}, {"value": -2, "name": "Nerlens Noel"}, {"value": 2, "name": "Marc Gasol"}, {"value": -2, "name": "Mason Plumlee"}]},
{"source": "https://playbook.draftkings.com/nba/nba-targets-January-27th-2", "targets": [{"value": 3, "name": "Stephen Curry"}, {"value": 3, "name": "Chris Paul"}, {"value": 1, "name": "Russell Westbrook"}, {"value": 1, "name": "Kemba Walker"}, {"value": 1, "name": "Isaiah Thomas"}, {"value": 1, "name": "Kyrie Irving"}, {"value": 2, "name": "Trey Burke"}, {"value": 2, "name": "UPDATE: Raul Neto will play tonight. This should limit the minutes of Rodney Hood and Trey Burke."}, {"value": 2, "name": "TJ McConnell"}, {"value": 1, "name": "Marcus Smart"}, {"value": 1, "name": "Zach LaVine"}, {"value": 3, "name": "James Harden"}, {"value": 3, "name": "Rodney Hood"}, {"value": 3, "name": "UPDATE: Raul Neto will play tonight. This should limit the minutes of Rodney Hood and Trey Burke."}, {"value": 1, "name": "Andrew Wiggins"}, {"value": 1, "name": "Avery Bradley"}, {"value": 2, "name": "Archie Goodwin"}, {"value": 2, "name": "Dion Waiters"}, {"value": 1, "name": "Nik Stauskas"}, {"value": 1, "name": "Gary Harris"}, {"value": 3, "name": "LeBron James"}, {"value": 3, "name": "Kevin Durant"}, {"value": 1, "name": "Kawhi Leonard"}, {"value": 1, "name": "Jae Crowder"}, {"value": 2, "name": "Jonathan Simmons"}, {"value": 2, "name": "Shabazz Muhammad"}, {"value": 1, "name": "Thabo Sefolosha"}, {"value": 1, "name": "Paul Pierce"}, {"value": 3, "name": "Paul Millsap"}, {"value": 3, "name": "Nerlens Noel"}, {"value": 1, "name": "Kevin Love"}, {"value": 2, "name": "Josh Smith"}, {"value": 2, "name": "Richaud Holmes"}, {"value": 1, "name": "David West"}, {"value": 1, "name": "Anthony Tolliver"}, {"value": 3, "name": "Andre Drummond"}, {"value": 3, "name": "DeAndre Jordan"}, {"value": 1, "name": "Al Horford"}, {"value": 2, "name": "Spencer Hawes"}, {"value": 2, "name": "Aron Baynes"}, {"value": 1, "name": "Marreese Speights"}, {"value": 1, "name": "Salah Mejri"}]},
{"source": "https://playbook.draftkings.com/nba/nba-targets-January-27th-3", "targets": [{"value": 3, "name": "John Wall"}, {"value": 3, "name": "Kyrie Irving"}, {"value": 1, "name": "Isaiah Thomas"}, {"value": 1, "name": "Kyle Lowry"}, {"value": 2, "name": "Derrick Rose"}, {"value": 1, "name": "Malcolm Brogdon"}, {"value": 1, "name": "Patty Mills"}, {"value": 3, "name": "James Harden"}, {"value": 3, "name": "Jimmy Butler"}, {"value": 1, "name": "C.J. McCollum"}, {"value": 1, "name": "Dwyane Wade"}, {"value": 1, "name": "Bradley Beal"}, {"value": 2, "name": "Kent Bazemore"}, {"value": 1, "name": "Marcus Smart"}, {"value": 1, "name": "Caris LeVert"}, {"value": 3, "name": "LeBron James"}, {"value": 3, "name": "Giannis Antetokounmpo"}, {"value": 1, "name": "Paul George"}, {"value": 2, "name": "Aaron Gordon"}, {"value": 1, "name": "Robert Covington"}, {"value": 1, "name": "Trevor Ariza"}, {"value": 3, "name": "DeMarcus Cousins"}, {"value": 3, "name": "Markieff Morris"}, {"value": 1, "name": "Paul Millsap"}, {"value": 1, "name": "Jabari Parker"}, {"value": 2, "name": "JaMychal Green"}, {"value": 1, "name": "Marvin Williams"}, {"value": 1, "name": "Al-Farouq Aminu"}, {"value": 3, "name": "Anthony Davis"}, {"value": 3, "name": "Joel Embiid"}, {"value": 1, "name": "Kevin Love"}, {"value": 1, "name": "Marc Gasol"}, {"value": 2, "name": "Greg Monroe"}, {"value": 1, "name": "Jonas Valanciunas"}, {"value": 1, "name": "Robin Lopez"}]},
{"source": "https://playbook.draftkings.com/nba/nba-targets-January-27th", "targets": [{"value": 3, "name": "John Wall"}, {"value": 3, "name": ""}, {"value": 3, "name": "Mike Conley"}, {"value": 3, "name": "NOTE"}, {"value": 3, "name": ""}, {"value": 2, "name": "D.J. Augustin"}, {"value": 2, "name": ""}, {"value": 2, "name": "C.J. Watson"}, {"value": 2, "name": "_____________________"}, {"value": 2, "name": "SHOOTING GUARD TARGETS"}, {"value": 3, "name": "Monta Ellis"}, {"value": 3, "name": ""}, {"value": 3, "name": "DeMar DeRozan"}, {"value": 3, "name": ""}, {"value": 2, "name": "J.R. Smith"}, {"value": 2, "name": ""}, {"value": 2, "name": "Lou Williams"}, {"value": 2, "name": "_____________________"}, {"value": 2, "name": "SMALL FORWARD TARGETS"}, {"value": 3, "name": "LeBron James"}, {"value": 3, "name": ""}, {"value": 3, "name": "Draymond Green"}, {"value": 3, "name": ""}, {"value": 2, "name": "Luol Deng"}, {"value": 2, "name": "NOTE"}, {"value": 2, "name": ""}, {"value": 2, "name": "Paul Pierce"}, {"value": 2, "name": "_____________________"}, {"value": 2, "name": "POWER FORWARD TARGETS"}, {"value": 3, "name": "Pau Gasol"}, {"value": 3, "name": ""}, {"value": 3, "name": "Zach Randolph"}, {"value": 3, "name": ""}, {"value": 2, "name": "Nene Hilario"}, {"value": 2, "name": "_____________________"}, {"value": 2, "name": "CENTER TARGETS"}, {"value": 3, "name": "Marc Gasol"}, {"value": 3, "name": ""}, {"value": 3, "name": "Andre Drummond"}, {"value": 3, "name": ""}, {"value": 2, "name": "Jonas Valanciunas"}, {"value": 2, "name": ""}, {"value": 2, "name": "Hassan Whiteside"}, {"value": 2, "name": ""}, {"value": 2, "name": "Good luck on Tuesday! Catch me on Twitter"}, {"value": 2, "name": "View All Contributors"}]},
{"source": "https://playbook.draftkings.com/nba/nba-cheat-sheet-January-27th", "targets": [{"value": 0, "name": "Mavericks"}, {"value": 0, "name": "Hornets"}, {"value": 0, "name": "Nuggets"}, {"value": 0, "name": "Rockets"}, {"value": 1, "name": "Isaiah Thomas"}, {"value": -2, "name": "Jeff Teague"}, {"value": 1, "name": "Andrew Wiggins"}, {"value": -2, "name": "Devin Booker"}, {"value": 1, "name": "Kawhi Leonard"}, {"value": -2, "name": "Robert Covington"}, {"value": 1, "name": "LaMarcus Aldridge"}, {"value": -2, "name": "Alex Len"}, {"value": 1, "name": "Andre Dummond"}, {"value": -2, "name": "Spencer Hawes"}]}
]